[
    {
        "projectId": "prj_i3UGYgIq7KLxZ2Un1RP6LTT9EtI0",
        "TimeUTC": "2026-02-14 09:34:37",
        "timestampInMs": 1771061677236,
        "requestPath": "vendly-api.vercel.app/favicon.ico",
        "requestMethod": "GET",
        "requestQueryString": "",
        "responseStatusCode": 500,
        "requestId": "r44wd-1771061676943-90094f35525e",
        "requestUserAgent": "Mozilla/5.0 (Windows NT 10.0; Win64; x64) AppleWebKit/537.36 (KHTML, like Gecko) Chrome/144.0.0.0 Safari/537.36",
        "environment": "production",
        "branch": "main",
        "vercelCache": "MISS",
        "host": "vendly-api.vercel.app",
        "deploymentDomain": "vendly-api.vercel.app",
        "deploymentId": "dpl_EmTYLywybLy2yFBkrVU2L352dgdw",
        "traceId": "",
        "sessionId": "",
        "type": "function",
        "function": "/favicon.ico",
        "level": "error",
        "message": "Error [ERR_MODULE_NOT_FOUND]: Cannot find module '/var/task/apps/api/src/routes/api-router' imported from /var/task/apps/api/src/app.js\n    at finalizeResolution (node:internal/modules/esm/resolve:280:11)\n    at moduleResolve (node:internal/modules/esm/resolve:865:10)\n    at moduleResolveWithNodePath (node:internal/modules/esm/resolve:989:14)\n    at defaultResolve (node:internal/modules/esm/resolve:1032:79)\n    at #cachedDefaultResolve (node:internal/modules/esm/loader:731:20)\n    at ModuleLoader.resolve (node:internal/modules/esm/loader:708:38)\n    at ModuleLoader.getModuleJobForImport (node:internal/modules/esm/loader:310:38)\n    at ModuleJob._link (node:internal/modules/esm/module_job:182:49)\n    at process.processTicksAndRejections (node:internal/process/task_queues:105:5) {\n  code: 'ERR_MODULE_NOT_FOUND',\n  url: 'file:///var/task/apps/api/src/routes/api-router'\n}\nNode.js process exited with exit status: 1. The logs above can help with debugging the issue.",
        "durationMs": "",
        "region": "",
        "maxMemoryUsed": "",
        "memorySize": "",
        "invocationId": "",
        "instanceId": "",
        "concurrency": ""
    },
    {
        "projectId": "prj_i3UGYgIq7KLxZ2Un1RP6LTT9EtI0",
        "TimeUTC": "2026-02-14 09:34:36",
        "timestampInMs": 1771061676943,
        "requestPath": "vendly-api.vercel.app/favicon.ico",
        "requestMethod": "GET",
        "requestQueryString": "",
        "responseStatusCode": 500,
        "requestId": "r44wd-1771061676943-90094f35525e",
        "requestUserAgent": "Mozilla/5.0 (Windows NT 10.0; Win64; x64) AppleWebKit/537.36 (KHTML, like Gecko) Chrome/144.0.0.0 Safari/537.36",
        "environment": "production",
        "branch": "main",
        "vercelCache": "MISS",
        "host": "vendly-api.vercel.app",
        "deploymentDomain": "vendly-api.vercel.app",
        "deploymentId": "dpl_EmTYLywybLy2yFBkrVU2L352dgdw",
        "traceId": "",
        "sessionId": "",
        "type": "function",
        "function": "/",
        "level": "",
        "message": "",
        "durationMs": 157,
        "region": "iad1",
        "maxMemoryUsed": -1,
        "memorySize": 2048,
        "invocationId": "01KHDR1307EA4ZZC8GN6JD86JW",
        "instanceId": "",
        "concurrency": -1
    },
    {
        "projectId": "prj_i3UGYgIq7KLxZ2Un1RP6LTT9EtI0",
        "TimeUTC": "2026-02-14 09:34:36",
        "timestampInMs": 1771061676476,
        "requestPath": "vendly-api.vercel.app/",
        "requestMethod": "GET",
        "requestQueryString": "",
        "responseStatusCode": 500,
        "requestId": "r44wd-1771061675479-17287945f01a",
        "requestUserAgent": "Mozilla/5.0 (Windows NT 10.0; Win64; x64) AppleWebKit/537.36 (KHTML, like Gecko) Chrome/144.0.0.0 Safari/537.36",
        "environment": "production",
        "branch": "main",
        "vercelCache": "MISS",
        "host": "vendly-api.vercel.app",
        "deploymentDomain": "vendly-api.vercel.app",
        "deploymentId": "dpl_EmTYLywybLy2yFBkrVU2L352dgdw",
        "traceId": "",
        "sessionId": "",
        "type": "function",
        "function": "/",
        "level": "error",
        "message": "Error [ERR_MODULE_NOT_FOUND]: Cannot find module '/var/task/apps/api/src/routes/api-router' imported from /var/task/apps/api/src/app.js\n    at finalizeResolution (node:internal/modules/esm/resolve:280:11)\n    at moduleResolve (node:internal/modules/esm/resolve:865:10)\n    at moduleResolveWithNodePath (node:internal/modules/esm/resolve:989:14)\n    at defaultResolve (node:internal/modules/esm/resolve:1032:79)\n    at #cachedDefaultResolve (node:internal/modules/esm/loader:731:20)\n    at ModuleLoader.resolve (node:internal/modules/esm/loader:708:38)\n    at ModuleLoader.getModuleJobForImport (node:internal/modules/esm/loader:310:38)\n    at ModuleJob._link (node:internal/modules/esm/module_job:182:49)\n    at process.processTicksAndRejections (node:internal/process/task_queues:105:5) {\n  code: 'ERR_MODULE_NOT_FOUND',\n  url: 'file:///var/task/apps/api/src/routes/api-router'\n}\nNode.js process exited with exit status: 1. The logs above can help with debugging the issue.",
        "durationMs": "",
        "region": "",
        "maxMemoryUsed": "",
        "memorySize": "",
        "invocationId": "",
        "instanceId": "",
        "concurrency": ""
    },
    {
        "projectId": "prj_i3UGYgIq7KLxZ2Un1RP6LTT9EtI0",
        "TimeUTC": "2026-02-14 09:34:35",
        "timestampInMs": 1771061675479,
        "requestPath": "vendly-api.vercel.app/",
        "requestMethod": "GET",
        "requestQueryString": "",
        "responseStatusCode": 500,
        "requestId": "r44wd-1771061675479-17287945f01a",
        "requestUserAgent": "Mozilla/5.0 (Windows NT 10.0; Win64; x64) AppleWebKit/537.36 (KHTML, like Gecko) Chrome/144.0.0.0 Safari/537.36",
        "environment": "production",
        "branch": "main",
        "vercelCache": "MISS",
        "host": "vendly-api.vercel.app",
        "deploymentDomain": "vendly-api.vercel.app",
        "deploymentId": "dpl_EmTYLywybLy2yFBkrVU2L352dgdw",
        "traceId": "",
        "sessionId": "",
        "type": "function",
        "function": "/",
        "level": "",
        "message": "",
        "durationMs": 154,
        "region": "iad1",
        "maxMemoryUsed": -1,
        "memorySize": 2048,
        "invocationId": "01KHDR128N032HK204QZDQJ5Y6",
        "instanceId": "",
        "concurrency": -1
    },
    {
        "projectId": "prj_i3UGYgIq7KLxZ2Un1RP6LTT9EtI0",
        "TimeUTC": "2026-02-14 09:34:29",
        "timestampInMs": 1771061669016,
        "requestPath": "vendly-api.vercel.app/favicon.ico",
        "requestMethod": "GET",
        "requestQueryString": "",
        "responseStatusCode": 500,
        "requestId": "4vvhx-1771061668453-f8cf9a63392c",
        "requestUserAgent": "Mozilla/5.0 (Windows NT 10.0; Win64; x64) AppleWebKit/537.36 (KHTML, like Gecko) Chrome/144.0.0.0 Safari/537.36",
        "environment": "production",
        "branch": "main",
        "vercelCache": "MISS",
        "host": "vendly-api.vercel.app",
        "deploymentDomain": "vendly-api.vercel.app",
        "deploymentId": "dpl_EmTYLywybLy2yFBkrVU2L352dgdw",
        "traceId": "",
        "sessionId": "",
        "type": "function",
        "function": "/favicon.ico",
        "level": "error",
        "message": "Error [ERR_MODULE_NOT_FOUND]: Cannot find module '/var/task/apps/api/src/routes/api-router' imported from /var/task/apps/api/src/app.js\n    at finalizeResolution (node:internal/modules/esm/resolve:280:11)\n    at moduleResolve (node:internal/modules/esm/resolve:865:10)\n    at moduleResolveWithNodePath (node:internal/modules/esm/resolve:989:14)\n    at defaultResolve (node:internal/modules/esm/resolve:1032:79)\n    at #cachedDefaultResolve (node:internal/modules/esm/loader:731:20)\n    at ModuleLoader.resolve (node:internal/modules/esm/loader:708:38)\n    at ModuleLoader.getModuleJobForImport (node:internal/modules/esm/loader:310:38)\n    at ModuleJob._link (node:internal/modules/esm/module_job:182:49)\n    at process.processTicksAndRejections (node:internal/process/task_queues:105:5) {\n  code: 'ERR_MODULE_NOT_FOUND',\n  url: 'file:///var/task/apps/api/src/routes/api-router'\n}\nNode.js process exited with exit status: 1. The logs above can help with debugging the issue.",
        "durationMs": "",
        "region": "",
        "maxMemoryUsed": "",
        "memorySize": "",
        "invocationId": "",
        "instanceId": "",
        "concurrency": ""
    },
    {
        "projectId": "prj_i3UGYgIq7KLxZ2Un1RP6LTT9EtI0",
        "TimeUTC": "2026-02-14 09:34:28",
        "timestampInMs": 1771061668453,
        "requestPath": "vendly-api.vercel.app/favicon.ico",
        "requestMethod": "GET",
        "requestQueryString": "",
        "responseStatusCode": 500,
        "requestId": "4vvhx-1771061668453-f8cf9a63392c",
        "requestUserAgent": "Mozilla/5.0 (Windows NT 10.0; Win64; x64) AppleWebKit/537.36 (KHTML, like Gecko) Chrome/144.0.0.0 Safari/537.36",
        "environment": "production",
        "branch": "main",
        "vercelCache": "MISS",
        "host": "vendly-api.vercel.app",
        "deploymentDomain": "vendly-api.vercel.app",
        "deploymentId": "dpl_EmTYLywybLy2yFBkrVU2L352dgdw",
        "traceId": "",
        "sessionId": "",
        "type": "function",
        "function": "/",
        "level": "",
        "message": "",
        "durationMs": 155,
        "region": "iad1",
        "maxMemoryUsed": -1,
        "memorySize": 2048,
        "invocationId": "01KHDR0TZFKYEWXYYF6T2DAJBQ",
        "instanceId": "",
        "concurrency": -1
    },
    {
        "projectId": "prj_i3UGYgIq7KLxZ2Un1RP6LTT9EtI0",
        "TimeUTC": "2026-02-14 09:34:27",
        "timestampInMs": 1771061667606,
        "requestPath": "vendly-api.vercel.app/",
        "requestMethod": "GET",
        "requestQueryString": "",
        "responseStatusCode": 500,
        "requestId": "bz7qv-1771061666664-ca16edbfdfc1",
        "requestUserAgent": "Mozilla/5.0 (Windows NT 10.0; Win64; x64) AppleWebKit/537.36 (KHTML, like Gecko) Chrome/144.0.0.0 Safari/537.36",
        "environment": "production",
        "branch": "main",
        "vercelCache": "MISS",
        "host": "vendly-api.vercel.app",
        "deploymentDomain": "vendly-fubvhldmt-jeremiah-sentomeros-projects.vercel.app",
        "deploymentId": "dpl_EmTYLywybLy2yFBkrVU2L352dgdw",
        "traceId": "",
        "sessionId": "",
        "type": "function",
        "function": "/",
        "level": "error",
        "message": "Error [ERR_MODULE_NOT_FOUND]: Cannot find module '/var/task/apps/api/src/routes/api-router' imported from /var/task/apps/api/src/app.js\n    at finalizeResolution (node:internal/modules/esm/resolve:280:11)\n    at moduleResolve (node:internal/modules/esm/resolve:865:10)\n    at moduleResolveWithNodePath (node:internal/modules/esm/resolve:989:14)\n    at defaultResolve (node:internal/modules/esm/resolve:1032:79)\n    at #cachedDefaultResolve (node:internal/modules/esm/loader:731:20)\n    at ModuleLoader.resolve (node:internal/modules/esm/loader:708:38)\n    at ModuleLoader.getModuleJobForImport (node:internal/modules/esm/loader:310:38)\n    at ModuleJob._link (node:internal/modules/esm/module_job:182:49)\n    at process.processTicksAndRejections (node:internal/process/task_queues:105:5) {\n  code: 'ERR_MODULE_NOT_FOUND',\n  url: 'file:///var/task/apps/api/src/routes/api-router'\n}\nNode.js process exited with exit status: 1. The logs above can help with debugging the issue.",
        "durationMs": "",
        "region": "",
        "maxMemoryUsed": "",
        "memorySize": "",
        "invocationId": "",
        "instanceId": "",
        "concurrency": ""
    },
    {
        "projectId": "prj_i3UGYgIq7KLxZ2Un1RP6LTT9EtI0",
        "TimeUTC": "2026-02-14 09:34:26",
        "timestampInMs": 1771061666664,
        "requestPath": "vendly-api.vercel.app/",
        "requestMethod": "GET",
        "requestQueryString": "",
        "responseStatusCode": 500,
        "requestId": "bz7qv-1771061666664-ca16edbfdfc1",
        "requestUserAgent": "Mozilla/5.0 (Windows NT 10.0; Win64; x64) AppleWebKit/537.36 (KHTML, like Gecko) Chrome/144.0.0.0 Safari/537.36",
        "environment": "production",
        "branch": "main",
        "vercelCache": "MISS",
        "host": "vendly-api.vercel.app",
        "deploymentDomain": "vendly-fubvhldmt-jeremiah-sentomeros-projects.vercel.app",
        "deploymentId": "dpl_EmTYLywybLy2yFBkrVU2L352dgdw",
        "traceId": "",
        "sessionId": "",
        "type": "function",
        "function": "/",
        "level": "",
        "message": "",
        "durationMs": 155,
        "region": "iad1",
        "maxMemoryUsed": -1,
        "memorySize": 2048,
        "invocationId": "01KHDR0SKBGXVC5MGJBK7ZCE0R",
        "instanceId": "",
        "concurrency": -1
    },
    {
        "projectId": "prj_i3UGYgIq7KLxZ2Un1RP6LTT9EtI0",
        "TimeUTC": "2026-02-14 09:34:18",
        "timestampInMs": 1771061658547,
        "requestPath": "vendly-fubvhldmt-jeremiah-sentomeros-projects.vercel.app/favicon.png",
        "requestMethod": "GET",
        "requestQueryString": "",
        "responseStatusCode": 500,
        "requestId": "pf87s-1771061658328-65e1b1dbb4bc",
        "requestUserAgent": "vercel-favicon/1.0",
        "environment": "production",
        "branch": "main",
        "vercelCache": "MISS",
        "host": "vendly-fubvhldmt-jeremiah-sentomeros-projects.vercel.app",
        "deploymentDomain": "vendly-fubvhldmt-jeremiah-sentomeros-projects.vercel.app",
        "deploymentId": "dpl_EmTYLywybLy2yFBkrVU2L352dgdw",
        "traceId": "",
        "sessionId": "",
        "type": "function",
        "function": "/favicon.png",
        "level": "error",
        "message": "Error [ERR_MODULE_NOT_FOUND]: Cannot find module '/var/task/apps/api/src/routes/api-router' imported from /var/task/apps/api/src/app.js\n    at finalizeResolution (node:internal/modules/esm/resolve:280:11)\n    at moduleResolve (node:internal/modules/esm/resolve:865:10)\n    at moduleResolveWithNodePath (node:internal/modules/esm/resolve:989:14)\n    at defaultResolve (node:internal/modules/esm/resolve:1032:79)\n    at #cachedDefaultResolve (node:internal/modules/esm/loader:731:20)\n    at ModuleLoader.resolve (node:internal/modules/esm/loader:708:38)\n    at ModuleLoader.getModuleJobForImport (node:internal/modules/esm/loader:310:38)\n    at ModuleJob._link (node:internal/modules/esm/module_job:182:49)\n    at process.processTicksAndRejections (node:internal/process/task_queues:105:5) {\n  code: 'ERR_MODULE_NOT_FOUND',\n  url: 'file:///var/task/apps/api/src/routes/api-router'\n}\nNode.js process exited with exit status: 1. The logs above can help with debugging the issue.",
        "durationMs": "",
        "region": "",
        "maxMemoryUsed": "",
        "memorySize": "",
        "invocationId": "",
        "instanceId": "",
        "concurrency": ""
    },
    {
        "projectId": "prj_i3UGYgIq7KLxZ2Un1RP6LTT9EtI0",
        "TimeUTC": "2026-02-14 09:34:18",
        "timestampInMs": 1771061658328,
        "requestPath": "vendly-fubvhldmt-jeremiah-sentomeros-projects.vercel.app/favicon.png",
        "requestMethod": "GET",
        "requestQueryString": "",
        "responseStatusCode": 500,
        "requestId": "pf87s-1771061658328-65e1b1dbb4bc",
        "requestUserAgent": "vercel-favicon/1.0",
        "environment": "production",
        "branch": "main",
        "vercelCache": "MISS",
        "host": "vendly-fubvhldmt-jeremiah-sentomeros-projects.vercel.app",
        "deploymentDomain": "vendly-fubvhldmt-jeremiah-sentomeros-projects.vercel.app",
        "deploymentId": "dpl_EmTYLywybLy2yFBkrVU2L352dgdw",
        "traceId": "",
        "sessionId": "",
        "type": "function",
        "function": "/",
        "level": "",
        "message": "",
        "durationMs": 158,
        "region": "iad1",
        "maxMemoryUsed": -1,
        "memorySize": 2048,
        "invocationId": "01KHDR0GR82V1H70KMTBSBE5WQ",
        "instanceId": "",
        "concurrency": -1
    },
    {
        "projectId": "prj_i3UGYgIq7KLxZ2Un1RP6LTT9EtI0",
        "TimeUTC": "2026-02-14 09:34:16",
        "timestampInMs": 1771061656154,
        "requestPath": "vendly-fubvhldmt-jeremiah-sentomeros-projects.vercel.app/favicon.png",
        "requestMethod": "GET",
        "requestQueryString": "",
        "responseStatusCode": 500,
        "requestId": "dcqth-1771061655935-85f27ff35529",
        "requestUserAgent": "vercel-favicon/1.0",
        "environment": "production",
        "branch": "main",
        "vercelCache": "MISS",
        "host": "vendly-fubvhldmt-jeremiah-sentomeros-projects.vercel.app",
        "deploymentDomain": "vendly-fubvhldmt-jeremiah-sentomeros-projects.vercel.app",
        "deploymentId": "dpl_EmTYLywybLy2yFBkrVU2L352dgdw",
        "traceId": "",
        "sessionId": "",
        "type": "function",
        "function": "/favicon.png",
        "level": "error",
        "message": "Error [ERR_MODULE_NOT_FOUND]: Cannot find module '/var/task/apps/api/src/routes/api-router' imported from /var/task/apps/api/src/app.js\n    at finalizeResolution (node:internal/modules/esm/resolve:280:11)\n    at moduleResolve (node:internal/modules/esm/resolve:865:10)\n    at moduleResolveWithNodePath (node:internal/modules/esm/resolve:989:14)\n    at defaultResolve (node:internal/modules/esm/resolve:1032:79)\n    at #cachedDefaultResolve (node:internal/modules/esm/loader:731:20)\n    at ModuleLoader.resolve (node:internal/modules/esm/loader:708:38)\n    at ModuleLoader.getModuleJobForImport (node:internal/modules/esm/loader:310:38)\n    at ModuleJob._link (node:internal/modules/esm/module_job:182:49)\n    at process.processTicksAndRejections (node:internal/process/task_queues:105:5) {\n  code: 'ERR_MODULE_NOT_FOUND',\n  url: 'file:///var/task/apps/api/src/routes/api-router'\n}\nNode.js process exited with exit status: 1. The logs above can help with debugging the issue.",
        "durationMs": "",
        "region": "",
        "maxMemoryUsed": "",
        "memorySize": "",
        "invocationId": "",
        "instanceId": "",
        "concurrency": ""
    },
    {
        "projectId": "prj_i3UGYgIq7KLxZ2Un1RP6LTT9EtI0",
        "TimeUTC": "2026-02-14 09:34:15",
        "timestampInMs": 1771061655935,
        "requestPath": "vendly-fubvhldmt-jeremiah-sentomeros-projects.vercel.app/favicon.png",
        "requestMethod": "GET",
        "requestQueryString": "",
        "responseStatusCode": 500,
        "requestId": "dcqth-1771061655935-85f27ff35529",
        "requestUserAgent": "vercel-favicon/1.0",
        "environment": "production",
        "branch": "main",
        "vercelCache": "MISS",
        "host": "vendly-fubvhldmt-jeremiah-sentomeros-projects.vercel.app",
        "deploymentDomain": "vendly-fubvhldmt-jeremiah-sentomeros-projects.vercel.app",
        "deploymentId": "dpl_EmTYLywybLy2yFBkrVU2L352dgdw",
        "traceId": "",
        "sessionId": "",
        "type": "function",
        "function": "/",
        "level": "",
        "message": "",
        "durationMs": 158,
        "region": "iad1",
        "maxMemoryUsed": -1,
        "memorySize": 2048,
        "invocationId": "01KHDR0ED7YC9V7A58ZAGG6798",
        "instanceId": "",
        "concurrency": -1
    },
    {
        "projectId": "prj_i3UGYgIq7KLxZ2Un1RP6LTT9EtI0",
        "TimeUTC": "2026-02-14 09:34:14",
        "timestampInMs": 1771061654836,
        "requestPath": "vendly-fubvhldmt-jeremiah-sentomeros-projects.vercel.app/favicon.png",
        "requestMethod": "GET",
        "requestQueryString": "",
        "responseStatusCode": "",
        "requestId": "kf2ls-1771061654531-f0f11e096be5",
        "requestUserAgent": "vercel-favicon/1.0",
        "environment": "production",
        "branch": "main",
        "vercelCache": "",
        "host": "vendly-fubvhldmt-jeremiah-sentomeros-projects.vercel.app",
        "deploymentDomain": "vendly-fubvhldmt-jeremiah-sentomeros-projects.vercel.app",
        "deploymentId": "dpl_EmTYLywybLy2yFBkrVU2L352dgdw",
        "traceId": "",
        "sessionId": "",
        "type": "function",
        "function": "",
        "level": "error",
        "message": "Error [ERR_MODULE_NOT_FOUND]: Cannot find module '/var/task/apps/api/src/routes/api-router' imported from /var/task/apps/api/src/app.js\n    at finalizeResolution (node:internal/modules/esm/resolve:280:11)\n    at moduleResolve (node:internal/modules/esm/resolve:865:10)\n    at moduleResolveWithNodePath (node:internal/modules/esm/resolve:989:14)\n    at defaultResolve (node:internal/modules/esm/resolve:1032:79)\n    at #cachedDefaultResolve (node:internal/modules/esm/loader:731:20)\n    at ModuleLoader.resolve (node:internal/modules/esm/loader:708:38)\n    at ModuleLoader.getModuleJobForImport (node:internal/modules/esm/loader:310:38)\n    at ModuleJob._link (node:internal/modules/esm/module_job:182:49)\n    at process.processTicksAndRejections (node:internal/process/task_queues:105:5) {\n  code: 'ERR_MODULE_NOT_FOUND',\n  url: 'file:///var/task/apps/api/src/routes/api-router'\n}\nNode.js process exited with exit status: 1. The logs above can help with debugging the issue.",
        "durationMs": "",
        "region": "",
        "maxMemoryUsed": "",
        "memorySize": "",
        "invocationId": "",
        "instanceId": "",
        "concurrency": ""
    },
    {
        "projectId": "prj_i3UGYgIq7KLxZ2Un1RP6LTT9EtI0",
        "TimeUTC": "2026-02-14 09:34:14",
        "timestampInMs": 1771061654531,
        "requestPath": "vendly-fubvhldmt-jeremiah-sentomeros-projects.vercel.app/favicon.png",
        "requestMethod": "GET",
        "requestQueryString": "",
        "responseStatusCode": "",
        "requestId": "kf2ls-1771061654531-f0f11e096be5",
        "requestUserAgent": "vercel-favicon/1.0",
        "environment": "production",
        "branch": "main",
        "vercelCache": "",
        "host": "vendly-fubvhldmt-jeremiah-sentomeros-projects.vercel.app",
        "deploymentDomain": "vendly-fubvhldmt-jeremiah-sentomeros-projects.vercel.app",
        "deploymentId": "dpl_EmTYLywybLy2yFBkrVU2L352dgdw",
        "traceId": "",
        "sessionId": "",
        "type": "function",
        "function": "/",
        "level": "",
        "message": "",
        "durationMs": 158,
        "region": "iad1",
        "maxMemoryUsed": -1,
        "memorySize": 2048,
        "invocationId": "01KHDR0D47RYV7AMA02NJVVS00",
        "instanceId": "",
        "concurrency": -1
    },
    {
        "projectId": "prj_i3UGYgIq7KLxZ2Un1RP6LTT9EtI0",
        "TimeUTC": "2026-02-14 09:34:14",
        "timestampInMs": 1771061654497,
        "requestPath": "vendly-fubvhldmt-jeremiah-sentomeros-projects.vercel.app/favicon.ico",
        "requestMethod": "GET",
        "requestQueryString": "",
        "responseStatusCode": "",
        "requestId": "cctt4-1771061654290-7fdf7c1867b4",
        "requestUserAgent": "vercel-favicon/1.0",
        "environment": "production",
        "branch": "main",
        "vercelCache": "",
        "host": "vendly-fubvhldmt-jeremiah-sentomeros-projects.vercel.app",
        "deploymentDomain": "vendly-fubvhldmt-jeremiah-sentomeros-projects.vercel.app",
        "deploymentId": "dpl_EmTYLywybLy2yFBkrVU2L352dgdw",
        "traceId": "",
        "sessionId": "",
        "type": "function",
        "function": "",
        "level": "error",
        "message": "Error [ERR_MODULE_NOT_FOUND]: Cannot find module '/var/task/apps/api/src/routes/api-router' imported from /var/task/apps/api/src/app.js\n    at finalizeResolution (node:internal/modules/esm/resolve:280:11)\n    at moduleResolve (node:internal/modules/esm/resolve:865:10)\n    at moduleResolveWithNodePath (node:internal/modules/esm/resolve:989:14)\n    at defaultResolve (node:internal/modules/esm/resolve:1032:79)\n    at #cachedDefaultResolve (node:internal/modules/esm/loader:731:20)\n    at ModuleLoader.resolve (node:internal/modules/esm/loader:708:38)\n    at ModuleLoader.getModuleJobForImport (node:internal/modules/esm/loader:310:38)\n    at ModuleJob._link (node:internal/modules/esm/module_job:182:49)\n    at process.processTicksAndRejections (node:internal/process/task_queues:105:5) {\n  code: 'ERR_MODULE_NOT_FOUND',\n  url: 'file:///var/task/apps/api/src/routes/api-router'\n}\nNode.js process exited with exit status: 1. The logs above can help with debugging the issue.",
        "durationMs": "",
        "region": "",
        "maxMemoryUsed": "",
        "memorySize": "",
        "invocationId": "",
        "instanceId": "",
        "concurrency": ""
    },
    {
        "projectId": "prj_i3UGYgIq7KLxZ2Un1RP6LTT9EtI0",
        "TimeUTC": "2026-02-14 09:34:14",
        "timestampInMs": 1771061654290,
        "requestPath": "vendly-fubvhldmt-jeremiah-sentomeros-projects.vercel.app/favicon.ico",
        "requestMethod": "GET",
        "requestQueryString": "",
        "responseStatusCode": "",
        "requestId": "cctt4-1771061654290-7fdf7c1867b4",
        "requestUserAgent": "vercel-favicon/1.0",
        "environment": "production",
        "branch": "main",
        "vercelCache": "",
        "host": "vendly-fubvhldmt-jeremiah-sentomeros-projects.vercel.app",
        "deploymentDomain": "vendly-fubvhldmt-jeremiah-sentomeros-projects.vercel.app",
        "deploymentId": "dpl_EmTYLywybLy2yFBkrVU2L352dgdw",
        "traceId": "",
        "sessionId": "",
        "type": "function",
        "function": "/",
        "level": "",
        "message": "",
        "durationMs": 157,
        "region": "iad1",
        "maxMemoryUsed": -1,
        "memorySize": 2048,
        "invocationId": "01KHDR0CSQPV681J6S713DQYJP",
        "instanceId": "",
        "concurrency": -1
    },
    {
        "projectId": "prj_i3UGYgIq7KLxZ2Un1RP6LTT9EtI0",
        "TimeUTC": "2026-02-14 09:34:12",
        "timestampInMs": 1771061652159,
        "requestPath": "vendly-fubvhldmt-jeremiah-sentomeros-projects.vercel.app/favicon.ico",
        "requestMethod": "GET",
        "requestQueryString": "",
        "responseStatusCode": 500,
        "requestId": "tvjxm-1771061651855-22fdc722db11",
        "requestUserAgent": "vercel-favicon/1.0",
        "environment": "production",
        "branch": "main",
        "vercelCache": "MISS",
        "host": "vendly-fubvhldmt-jeremiah-sentomeros-projects.vercel.app",
        "deploymentDomain": "vendly-fubvhldmt-jeremiah-sentomeros-projects.vercel.app",
        "deploymentId": "dpl_EmTYLywybLy2yFBkrVU2L352dgdw",
        "traceId": "",
        "sessionId": "",
        "type": "function",
        "function": "/favicon.ico",
        "level": "error",
        "message": "Error [ERR_MODULE_NOT_FOUND]: Cannot find module '/var/task/apps/api/src/routes/api-router' imported from /var/task/apps/api/src/app.js\n    at finalizeResolution (node:internal/modules/esm/resolve:280:11)\n    at moduleResolve (node:internal/modules/esm/resolve:865:10)\n    at moduleResolveWithNodePath (node:internal/modules/esm/resolve:989:14)\n    at defaultResolve (node:internal/modules/esm/resolve:1032:79)\n    at #cachedDefaultResolve (node:internal/modules/esm/loader:731:20)\n    at ModuleLoader.resolve (node:internal/modules/esm/loader:708:38)\n    at ModuleLoader.getModuleJobForImport (node:internal/modules/esm/loader:310:38)\n    at ModuleJob._link (node:internal/modules/esm/module_job:182:49)\n    at process.processTicksAndRejections (node:internal/process/task_queues:105:5) {\n  code: 'ERR_MODULE_NOT_FOUND',\n  url: 'file:///var/task/apps/api/src/routes/api-router'\n}\nNode.js process exited with exit status: 1. The logs above can help with debugging the issue.",
        "durationMs": "",
        "region": "",
        "maxMemoryUsed": "",
        "memorySize": "",
        "invocationId": "",
        "instanceId": "",
        "concurrency": ""
    },
    {
        "projectId": "prj_i3UGYgIq7KLxZ2Un1RP6LTT9EtI0",
        "TimeUTC": "2026-02-14 09:34:11",
        "timestampInMs": 1771061651855,
        "requestPath": "vendly-fubvhldmt-jeremiah-sentomeros-projects.vercel.app/favicon.ico",
        "requestMethod": "GET",
        "requestQueryString": "",
        "responseStatusCode": 500,
        "requestId": "tvjxm-1771061651855-22fdc722db11",
        "requestUserAgent": "vercel-favicon/1.0",
        "environment": "production",
        "branch": "main",
        "vercelCache": "MISS",
        "host": "vendly-fubvhldmt-jeremiah-sentomeros-projects.vercel.app",
        "deploymentDomain": "vendly-fubvhldmt-jeremiah-sentomeros-projects.vercel.app",
        "deploymentId": "dpl_EmTYLywybLy2yFBkrVU2L352dgdw",
        "traceId": "",
        "sessionId": "",
        "type": "function",
        "function": "/",
        "level": "",
        "message": "",
        "durationMs": 159,
        "region": "iad1",
        "maxMemoryUsed": -1,
        "memorySize": 2048,
        "invocationId": "01KHDR0AGJ57W92G5Q6233CC11",
        "instanceId": "",
        "concurrency": -1
    },
    {
        "projectId": "prj_i3UGYgIq7KLxZ2Un1RP6LTT9EtI0",
        "TimeUTC": "2026-02-14 09:34:10",
        "timestampInMs": 1771061650796,
        "requestPath": "vendly-fubvhldmt-jeremiah-sentomeros-projects.vercel.app/favicon.ico",
        "requestMethod": "GET",
        "requestQueryString": "",
        "responseStatusCode": 500,
        "requestId": "jclxd-1771061650471-2efae5f7ed23",
        "requestUserAgent": "vercel-favicon/1.0",
        "environment": "production",
        "branch": "main",
        "vercelCache": "MISS",
        "host": "vendly-fubvhldmt-jeremiah-sentomeros-projects.vercel.app",
        "deploymentDomain": "vendly-fubvhldmt-jeremiah-sentomeros-projects.vercel.app",
        "deploymentId": "dpl_EmTYLywybLy2yFBkrVU2L352dgdw",
        "traceId": "",
        "sessionId": "",
        "type": "function",
        "function": "/favicon.ico",
        "level": "error",
        "message": "Error [ERR_MODULE_NOT_FOUND]: Cannot find module '/var/task/apps/api/src/routes/api-router' imported from /var/task/apps/api/src/app.js\n    at finalizeResolution (node:internal/modules/esm/resolve:280:11)\n    at moduleResolve (node:internal/modules/esm/resolve:865:10)\n    at moduleResolveWithNodePath (node:internal/modules/esm/resolve:989:14)\n    at defaultResolve (node:internal/modules/esm/resolve:1032:79)\n    at #cachedDefaultResolve (node:internal/modules/esm/loader:731:20)\n    at ModuleLoader.resolve (node:internal/modules/esm/loader:708:38)\n    at ModuleLoader.getModuleJobForImport (node:internal/modules/esm/loader:310:38)\n    at ModuleJob._link (node:internal/modules/esm/module_job:182:49)\n    at process.processTicksAndRejections (node:internal/process/task_queues:105:5) {\n  code: 'ERR_MODULE_NOT_FOUND',\n  url: 'file:///var/task/apps/api/src/routes/api-router'\n}\nNode.js process exited with exit status: 1. The logs above can help with debugging the issue.",
        "durationMs": "",
        "region": "",
        "maxMemoryUsed": "",
        "memorySize": "",
        "invocationId": "",
        "instanceId": "",
        "concurrency": ""
    },
    {
        "projectId": "prj_i3UGYgIq7KLxZ2Un1RP6LTT9EtI0",
        "TimeUTC": "2026-02-14 09:34:10",
        "timestampInMs": 1771061650471,
        "requestPath": "vendly-fubvhldmt-jeremiah-sentomeros-projects.vercel.app/favicon.ico",
        "requestMethod": "GET",
        "requestQueryString": "",
        "responseStatusCode": 500,
        "requestId": "jclxd-1771061650471-2efae5f7ed23",
        "requestUserAgent": "vercel-favicon/1.0",
        "environment": "production",
        "branch": "main",
        "vercelCache": "MISS",
        "host": "vendly-fubvhldmt-jeremiah-sentomeros-projects.vercel.app",
        "deploymentDomain": "vendly-fubvhldmt-jeremiah-sentomeros-projects.vercel.app",
        "deploymentId": "dpl_EmTYLywybLy2yFBkrVU2L352dgdw",
        "traceId": "",
        "sessionId": "",
        "type": "function",
        "function": "/",
        "level": "",
        "message": "",
        "durationMs": 174,
        "region": "iad1",
        "maxMemoryUsed": -1,
        "memorySize": 2048,
        "invocationId": "01KHDR095EX06PB7H3VJVJ556K",
        "instanceId": "",
        "concurrency": -1
    },
    {
        "projectId": "prj_i3UGYgIq7KLxZ2Un1RP6LTT9EtI0",
        "TimeUTC": "2026-02-14 09:34:10",
        "timestampInMs": 1771061650350,
        "requestPath": "vendly-fubvhldmt-jeremiah-sentomeros-projects.vercel.app/",
        "requestMethod": "GET",
        "requestQueryString": "",
        "responseStatusCode": "",
        "requestId": "5xm8w-1771061650135-fab5ef32d213",
        "requestUserAgent": "vercel-favicon/1.0",
        "environment": "production",
        "branch": "main",
        "vercelCache": "",
        "host": "vendly-fubvhldmt-jeremiah-sentomeros-projects.vercel.app",
        "deploymentDomain": "vendly-fubvhldmt-jeremiah-sentomeros-projects.vercel.app",
        "deploymentId": "dpl_EmTYLywybLy2yFBkrVU2L352dgdw",
        "traceId": "",
        "sessionId": "",
        "type": "function",
        "function": "",
        "level": "error",
        "message": "Error [ERR_MODULE_NOT_FOUND]: Cannot find module '/var/task/apps/api/src/routes/api-router' imported from /var/task/apps/api/src/app.js\n    at finalizeResolution (node:internal/modules/esm/resolve:280:11)\n    at moduleResolve (node:internal/modules/esm/resolve:865:10)\n    at moduleResolveWithNodePath (node:internal/modules/esm/resolve:989:14)\n    at defaultResolve (node:internal/modules/esm/resolve:1032:79)\n    at #cachedDefaultResolve (node:internal/modules/esm/loader:731:20)\n    at ModuleLoader.resolve (node:internal/modules/esm/loader:708:38)\n    at ModuleLoader.getModuleJobForImport (node:internal/modules/esm/loader:310:38)\n    at ModuleJob._link (node:internal/modules/esm/module_job:182:49)\n    at process.processTicksAndRejections (node:internal/process/task_queues:105:5) {\n  code: 'ERR_MODULE_NOT_FOUND',\n  url: 'file:///var/task/apps/api/src/routes/api-router'\n}\nNode.js process exited with exit status: 1. The logs above can help with debugging the issue.",
        "durationMs": "",
        "region": "",
        "maxMemoryUsed": "",
        "memorySize": "",
        "invocationId": "",
        "instanceId": "",
        "concurrency": ""
    },
    {
        "projectId": "prj_i3UGYgIq7KLxZ2Un1RP6LTT9EtI0",
        "TimeUTC": "2026-02-14 09:34:10",
        "timestampInMs": 1771061650135,
        "requestPath": "vendly-fubvhldmt-jeremiah-sentomeros-projects.vercel.app/",
        "requestMethod": "GET",
        "requestQueryString": "",
        "responseStatusCode": "",
        "requestId": "5xm8w-1771061650135-fab5ef32d213",
        "requestUserAgent": "vercel-favicon/1.0",
        "environment": "production",
        "branch": "main",
        "vercelCache": "",
        "host": "vendly-fubvhldmt-jeremiah-sentomeros-projects.vercel.app",
        "deploymentDomain": "vendly-fubvhldmt-jeremiah-sentomeros-projects.vercel.app",
        "deploymentId": "dpl_EmTYLywybLy2yFBkrVU2L352dgdw",
        "traceId": "",
        "sessionId": "",
        "type": "function",
        "function": "/",
        "level": "",
        "message": "",
        "durationMs": 157,
        "region": "iad1",
        "maxMemoryUsed": -1,
        "memorySize": 2048,
        "invocationId": "01KHDR08R00GP7QV8PNCYHGN8P",
        "instanceId": "",
        "concurrency": -1
    },
    {
        "projectId": "prj_i3UGYgIq7KLxZ2Un1RP6LTT9EtI0",
        "TimeUTC": "2026-02-14 09:34:09",
        "timestampInMs": 1771061649033,
        "requestPath": "vendly-fubvhldmt-jeremiah-sentomeros-projects.vercel.app/",
        "requestMethod": "GET",
        "requestQueryString": "",
        "responseStatusCode": 500,
        "requestId": "tdvlk-1771061648820-c0deb4b79fcf",
        "requestUserAgent": "vercel-favicon/1.0",
        "environment": "production",
        "branch": "main",
        "vercelCache": "MISS",
        "host": "vendly-fubvhldmt-jeremiah-sentomeros-projects.vercel.app",
        "deploymentDomain": "vendly-fubvhldmt-jeremiah-sentomeros-projects.vercel.app",
        "deploymentId": "dpl_EmTYLywybLy2yFBkrVU2L352dgdw",
        "traceId": "",
        "sessionId": "",
        "type": "function",
        "function": "/",
        "level": "error",
        "message": "Error [ERR_MODULE_NOT_FOUND]: Cannot find module '/var/task/apps/api/src/routes/api-router' imported from /var/task/apps/api/src/app.js\n    at finalizeResolution (node:internal/modules/esm/resolve:280:11)\n    at moduleResolve (node:internal/modules/esm/resolve:865:10)\n    at moduleResolveWithNodePath (node:internal/modules/esm/resolve:989:14)\n    at defaultResolve (node:internal/modules/esm/resolve:1032:79)\n    at #cachedDefaultResolve (node:internal/modules/esm/loader:731:20)\n    at ModuleLoader.resolve (node:internal/modules/esm/loader:708:38)\n    at ModuleLoader.getModuleJobForImport (node:internal/modules/esm/loader:310:38)\n    at ModuleJob._link (node:internal/modules/esm/module_job:182:49)\n    at process.processTicksAndRejections (node:internal/process/task_queues:105:5) {\n  code: 'ERR_MODULE_NOT_FOUND',\n  url: 'file:///var/task/apps/api/src/routes/api-router'\n}\nNode.js process exited with exit status: 1. The logs above can help with debugging the issue.",
        "durationMs": "",
        "region": "",
        "maxMemoryUsed": "",
        "memorySize": "",
        "invocationId": "",
        "instanceId": "",
        "concurrency": ""
    },
    {
        "projectId": "prj_i3UGYgIq7KLxZ2Un1RP6LTT9EtI0",
        "TimeUTC": "2026-02-14 09:34:08",
        "timestampInMs": 1771061648820,
        "requestPath": "vendly-fubvhldmt-jeremiah-sentomeros-projects.vercel.app/",
        "requestMethod": "GET",
        "requestQueryString": "",
        "responseStatusCode": 500,
        "requestId": "tdvlk-1771061648820-c0deb4b79fcf",
        "requestUserAgent": "vercel-favicon/1.0",
        "environment": "production",
        "branch": "main",
        "vercelCache": "MISS",
        "host": "vendly-fubvhldmt-jeremiah-sentomeros-projects.vercel.app",
        "deploymentDomain": "vendly-fubvhldmt-jeremiah-sentomeros-projects.vercel.app",
        "deploymentId": "dpl_EmTYLywybLy2yFBkrVU2L352dgdw",
        "traceId": "",
        "sessionId": "",
        "type": "function",
        "function": "/",
        "level": "",
        "message": "",
        "durationMs": 158,
        "region": "iad1",
        "maxMemoryUsed": -1,
        "memorySize": 2048,
        "invocationId": "01KHDR07EVTTKA4RXFSGCT44DA",
        "instanceId": "",
        "concurrency": -1
    },
    {
        "projectId": "prj_i3UGYgIq7KLxZ2Un1RP6LTT9EtI0",
        "TimeUTC": "2026-02-14 09:33:04",
        "timestampInMs": 1771061584597,
        "requestPath": "vendly-fubvhldmt-jeremiah-sentomeros-projects.vercel.app/favicon.ico",
        "requestMethod": "GET",
        "requestQueryString": "",
        "responseStatusCode": 500,
        "requestId": "7szbf-1771061584381-80ea3263415c",
        "requestUserAgent": "vercel-screenshot/1.0",
        "environment": "production",
        "branch": "main",
        "vercelCache": "MISS",
        "host": "vendly-fubvhldmt-jeremiah-sentomeros-projects.vercel.app",
        "deploymentDomain": "vendly-fubvhldmt-jeremiah-sentomeros-projects.vercel.app",
        "deploymentId": "dpl_EmTYLywybLy2yFBkrVU2L352dgdw",
        "traceId": "",
        "sessionId": "",
        "type": "function",
        "function": "/favicon.ico",
        "level": "error",
        "message": "Error [ERR_MODULE_NOT_FOUND]: Cannot find module '/var/task/apps/api/src/routes/api-router' imported from /var/task/apps/api/src/app.js\n    at finalizeResolution (node:internal/modules/esm/resolve:280:11)\n    at moduleResolve (node:internal/modules/esm/resolve:865:10)\n    at moduleResolveWithNodePath (node:internal/modules/esm/resolve:989:14)\n    at defaultResolve (node:internal/modules/esm/resolve:1032:79)\n    at #cachedDefaultResolve (node:internal/modules/esm/loader:731:20)\n    at ModuleLoader.resolve (node:internal/modules/esm/loader:708:38)\n    at ModuleLoader.getModuleJobForImport (node:internal/modules/esm/loader:310:38)\n    at ModuleJob._link (node:internal/modules/esm/module_job:182:49)\n    at process.processTicksAndRejections (node:internal/process/task_queues:105:5) {\n  code: 'ERR_MODULE_NOT_FOUND',\n  url: 'file:///var/task/apps/api/src/routes/api-router'\n}\nNode.js process exited with exit status: 1. The logs above can help with debugging the issue.",
        "durationMs": "",
        "region": "",
        "maxMemoryUsed": "",
        "memorySize": "",
        "invocationId": "",
        "instanceId": "",
        "concurrency": ""
    },
    {
        "projectId": "prj_i3UGYgIq7KLxZ2Un1RP6LTT9EtI0",
        "TimeUTC": "2026-02-14 09:33:04",
        "timestampInMs": 1771061584381,
        "requestPath": "vendly-fubvhldmt-jeremiah-sentomeros-projects.vercel.app/favicon.ico",
        "requestMethod": "GET",
        "requestQueryString": "",
        "responseStatusCode": 500,
        "requestId": "7szbf-1771061584381-80ea3263415c",
        "requestUserAgent": "vercel-screenshot/1.0",
        "environment": "production",
        "branch": "main",
        "vercelCache": "MISS",
        "host": "vendly-fubvhldmt-jeremiah-sentomeros-projects.vercel.app",
        "deploymentDomain": "vendly-fubvhldmt-jeremiah-sentomeros-projects.vercel.app",
        "deploymentId": "dpl_EmTYLywybLy2yFBkrVU2L352dgdw",
        "traceId": "",
        "sessionId": "",
        "type": "function",
        "function": "/",
        "level": "",
        "message": "",
        "durationMs": 162,
        "region": "iad1",
        "maxMemoryUsed": -1,
        "memorySize": 2048,
        "invocationId": "01KHDQY8H3KGCNYK64S3YAE2NC",
        "instanceId": "",
        "concurrency": -1
    },
    {
        "projectId": "prj_i3UGYgIq7KLxZ2Un1RP6LTT9EtI0",
        "TimeUTC": "2026-02-14 09:33:04",
        "timestampInMs": 1771061584597,
        "requestPath": "vendly-fubvhldmt-jeremiah-sentomeros-projects.vercel.app/favicon.ico",
        "requestMethod": "GET",
        "requestQueryString": "",
        "responseStatusCode": "",
        "requestId": "2s68l-1771061584380-4bb654a2a54e",
        "requestUserAgent": "vercel-screenshot/1.0",
        "environment": "production",
        "branch": "main",
        "vercelCache": "",
        "host": "vendly-fubvhldmt-jeremiah-sentomeros-projects.vercel.app",
        "deploymentDomain": "vendly-fubvhldmt-jeremiah-sentomeros-projects.vercel.app",
        "deploymentId": "dpl_EmTYLywybLy2yFBkrVU2L352dgdw",
        "traceId": "",
        "sessionId": "",
        "type": "function",
        "function": "",
        "level": "error",
        "message": "Error [ERR_MODULE_NOT_FOUND]: Cannot find module '/var/task/apps/api/src/routes/api-router' imported from /var/task/apps/api/src/app.js\n    at finalizeResolution (node:internal/modules/esm/resolve:280:11)\n    at moduleResolve (node:internal/modules/esm/resolve:865:10)\n    at moduleResolveWithNodePath (node:internal/modules/esm/resolve:989:14)\n    at defaultResolve (node:internal/modules/esm/resolve:1032:79)\n    at #cachedDefaultResolve (node:internal/modules/esm/loader:731:20)\n    at ModuleLoader.resolve (node:internal/modules/esm/loader:708:38)\n    at ModuleLoader.getModuleJobForImport (node:internal/modules/esm/loader:310:38)\n    at ModuleJob._link (node:internal/modules/esm/module_job:182:49)\n    at process.processTicksAndRejections (node:internal/process/task_queues:105:5) {\n  code: 'ERR_MODULE_NOT_FOUND',\n  url: 'file:///var/task/apps/api/src/routes/api-router'\n}\nNode.js process exited with exit status: 1. The logs above can help with debugging the issue.",
        "durationMs": "",
        "region": "",
        "maxMemoryUsed": "",
        "memorySize": "",
        "invocationId": "",
        "instanceId": "",
        "concurrency": ""
    },
    {
        "projectId": "prj_i3UGYgIq7KLxZ2Un1RP6LTT9EtI0",
        "TimeUTC": "2026-02-14 09:33:04",
        "timestampInMs": 1771061584380,
        "requestPath": "vendly-fubvhldmt-jeremiah-sentomeros-projects.vercel.app/favicon.ico",
        "requestMethod": "GET",
        "requestQueryString": "",
        "responseStatusCode": "",
        "requestId": "2s68l-1771061584380-4bb654a2a54e",
        "requestUserAgent": "vercel-screenshot/1.0",
        "environment": "production",
        "branch": "main",
        "vercelCache": "",
        "host": "vendly-fubvhldmt-jeremiah-sentomeros-projects.vercel.app",
        "deploymentDomain": "vendly-fubvhldmt-jeremiah-sentomeros-projects.vercel.app",
        "deploymentId": "dpl_EmTYLywybLy2yFBkrVU2L352dgdw",
        "traceId": "",
        "sessionId": "",
        "type": "function",
        "function": "/",
        "level": "",
        "message": "",
        "durationMs": 157,
        "region": "iad1",
        "maxMemoryUsed": -1,
        "memorySize": 2048,
        "invocationId": "01KHDQY8H0AKYEPHWA315TTPB1",
        "instanceId": "",
        "concurrency": -1
    },
    {
        "projectId": "prj_i3UGYgIq7KLxZ2Un1RP6LTT9EtI0",
        "TimeUTC": "2026-02-14 09:33:04",
        "timestampInMs": 1771061584320,
        "requestPath": "vendly-fubvhldmt-jeremiah-sentomeros-projects.vercel.app/",
        "requestMethod": "GET",
        "requestQueryString": "",
        "responseStatusCode": 500,
        "requestId": "6pmm2-1771061584108-55bd0a10c607",
        "requestUserAgent": "vercel-screenshot/1.0",
        "environment": "production",
        "branch": "main",
        "vercelCache": "MISS",
        "host": "vendly-fubvhldmt-jeremiah-sentomeros-projects.vercel.app",
        "deploymentDomain": "vendly-fubvhldmt-jeremiah-sentomeros-projects.vercel.app",
        "deploymentId": "dpl_EmTYLywybLy2yFBkrVU2L352dgdw",
        "traceId": "",
        "sessionId": "",
        "type": "function",
        "function": "/",
        "level": "error",
        "message": "Error [ERR_MODULE_NOT_FOUND]: Cannot find module '/var/task/apps/api/src/routes/api-router' imported from /var/task/apps/api/src/app.js\n    at finalizeResolution (node:internal/modules/esm/resolve:280:11)\n    at moduleResolve (node:internal/modules/esm/resolve:865:10)\n    at moduleResolveWithNodePath (node:internal/modules/esm/resolve:989:14)\n    at defaultResolve (node:internal/modules/esm/resolve:1032:79)\n    at #cachedDefaultResolve (node:internal/modules/esm/loader:731:20)\n    at ModuleLoader.resolve (node:internal/modules/esm/loader:708:38)\n    at ModuleLoader.getModuleJobForImport (node:internal/modules/esm/loader:310:38)\n    at ModuleJob._link (node:internal/modules/esm/module_job:182:49)\n    at process.processTicksAndRejections (node:internal/process/task_queues:105:5) {\n  code: 'ERR_MODULE_NOT_FOUND',\n  url: 'file:///var/task/apps/api/src/routes/api-router'\n}\nNode.js process exited with exit status: 1. The logs above can help with debugging the issue.",
        "durationMs": "",
        "region": "",
        "maxMemoryUsed": "",
        "memorySize": "",
        "invocationId": "",
        "instanceId": "",
        "concurrency": ""
    },
    {
        "projectId": "prj_i3UGYgIq7KLxZ2Un1RP6LTT9EtI0",
        "TimeUTC": "2026-02-14 09:33:04",
        "timestampInMs": 1771061584108,
        "requestPath": "vendly-fubvhldmt-jeremiah-sentomeros-projects.vercel.app/",
        "requestMethod": "GET",
        "requestQueryString": "",
        "responseStatusCode": 500,
        "requestId": "6pmm2-1771061584108-55bd0a10c607",
        "requestUserAgent": "vercel-screenshot/1.0",
        "environment": "production",
        "branch": "main",
        "vercelCache": "MISS",
        "host": "vendly-fubvhldmt-jeremiah-sentomeros-projects.vercel.app",
        "deploymentDomain": "vendly-fubvhldmt-jeremiah-sentomeros-projects.vercel.app",
        "deploymentId": "dpl_EmTYLywybLy2yFBkrVU2L352dgdw",
        "traceId": "",
        "sessionId": "",
        "type": "function",
        "function": "/",
        "level": "",
        "message": "",
        "durationMs": 160,
        "region": "iad1",
        "maxMemoryUsed": -1,
        "memorySize": 2048,
        "invocationId": "01KHDQY88FPQEH40C5JSM3HSV7",
        "instanceId": "",
        "concurrency": -1
    },
    {
        "projectId": "prj_i3UGYgIq7KLxZ2Un1RP6LTT9EtI0",
        "TimeUTC": "2026-02-14 09:33:04",
        "timestampInMs": 1771061584317,
        "requestPath": "vendly-fubvhldmt-jeremiah-sentomeros-projects.vercel.app/",
        "requestMethod": "GET",
        "requestQueryString": "",
        "responseStatusCode": 500,
        "requestId": "rvl2m-1771061584101-5f37820b2a01",
        "requestUserAgent": "vercel-screenshot/1.0",
        "environment": "production",
        "branch": "main",
        "vercelCache": "MISS",
        "host": "vendly-fubvhldmt-jeremiah-sentomeros-projects.vercel.app",
        "deploymentDomain": "vendly-fubvhldmt-jeremiah-sentomeros-projects.vercel.app",
        "deploymentId": "dpl_EmTYLywybLy2yFBkrVU2L352dgdw",
        "traceId": "",
        "sessionId": "",
        "type": "function",
        "function": "/",
        "level": "error",
        "message": "Error [ERR_MODULE_NOT_FOUND]: Cannot find module '/var/task/apps/api/src/routes/api-router' imported from /var/task/apps/api/src/app.js\n    at finalizeResolution (node:internal/modules/esm/resolve:280:11)\n    at moduleResolve (node:internal/modules/esm/resolve:865:10)\n    at moduleResolveWithNodePath (node:internal/modules/esm/resolve:989:14)\n    at defaultResolve (node:internal/modules/esm/resolve:1032:79)\n    at #cachedDefaultResolve (node:internal/modules/esm/loader:731:20)\n    at ModuleLoader.resolve (node:internal/modules/esm/loader:708:38)\n    at ModuleLoader.getModuleJobForImport (node:internal/modules/esm/loader:310:38)\n    at ModuleJob._link (node:internal/modules/esm/module_job:182:49)\n    at process.processTicksAndRejections (node:internal/process/task_queues:105:5) {\n  code: 'ERR_MODULE_NOT_FOUND',\n  url: 'file:///var/task/apps/api/src/routes/api-router'\n}\nNode.js process exited with exit status: 1. The logs above can help with debugging the issue.",
        "durationMs": "",
        "region": "",
        "maxMemoryUsed": "",
        "memorySize": "",
        "invocationId": "",
        "instanceId": "",
        "concurrency": ""
    },
    {
        "projectId": "prj_i3UGYgIq7KLxZ2Un1RP6LTT9EtI0",
        "TimeUTC": "2026-02-14 09:33:04",
        "timestampInMs": 1771061584101,
        "requestPath": "vendly-fubvhldmt-jeremiah-sentomeros-projects.vercel.app/",
        "requestMethod": "GET",
        "requestQueryString": "",
        "responseStatusCode": 500,
        "requestId": "rvl2m-1771061584101-5f37820b2a01",
        "requestUserAgent": "vercel-screenshot/1.0",
        "environment": "production",
        "branch": "main",
        "vercelCache": "MISS",
        "host": "vendly-fubvhldmt-jeremiah-sentomeros-projects.vercel.app",
        "deploymentDomain": "vendly-fubvhldmt-jeremiah-sentomeros-projects.vercel.app",
        "deploymentId": "dpl_EmTYLywybLy2yFBkrVU2L352dgdw",
        "traceId": "",
        "sessionId": "",
        "type": "function",
        "function": "/",
        "level": "",
        "message": "",
        "durationMs": 161,
        "region": "iad1",
        "maxMemoryUsed": -1,
        "memorySize": 2048,
        "invocationId": "01KHDQY889DB7SGARW6VBWYWSZ",
        "instanceId": "",
        "concurrency": -1
    },
    {
        "projectId": "prj_i3UGYgIq7KLxZ2Un1RP6LTT9EtI0",
        "TimeUTC": "2026-02-14 09:33:03",
        "timestampInMs": 1771061583999,
        "requestPath": "vendly-fubvhldmt-jeremiah-sentomeros-projects.vercel.app/",
        "requestMethod": "GET",
        "requestQueryString": "",
        "responseStatusCode": 500,
        "requestId": "x447b-1771061583305-ca0e5dd8f038",
        "requestUserAgent": "vercel-screenshot/1.0",
        "environment": "production",
        "branch": "main",
        "vercelCache": "MISS",
        "host": "vendly-fubvhldmt-jeremiah-sentomeros-projects.vercel.app",
        "deploymentDomain": "vendly-fubvhldmt-jeremiah-sentomeros-projects.vercel.app",
        "deploymentId": "dpl_EmTYLywybLy2yFBkrVU2L352dgdw",
        "traceId": "",
        "sessionId": "",
        "type": "function",
        "function": "/",
        "level": "error",
        "message": "Error [ERR_MODULE_NOT_FOUND]: Cannot find module '/var/task/apps/api/src/routes/api-router' imported from /var/task/apps/api/src/app.js\n    at finalizeResolution (node:internal/modules/esm/resolve:280:11)\n    at moduleResolve (node:internal/modules/esm/resolve:865:10)\n    at moduleResolveWithNodePath (node:internal/modules/esm/resolve:989:14)\n    at defaultResolve (node:internal/modules/esm/resolve:1032:79)\n    at #cachedDefaultResolve (node:internal/modules/esm/loader:731:20)\n    at ModuleLoader.resolve (node:internal/modules/esm/loader:708:38)\n    at ModuleLoader.getModuleJobForImport (node:internal/modules/esm/loader:310:38)\n    at ModuleJob._link (node:internal/modules/esm/module_job:182:49)\n    at process.processTicksAndRejections (node:internal/process/task_queues:105:5) {\n  code: 'ERR_MODULE_NOT_FOUND',\n  url: 'file:///var/task/apps/api/src/routes/api-router'\n}\nNode.js process exited with exit status: 1. The logs above can help with debugging the issue.\nError [ERR_MODULE_NOT_FOUND]: Cannot find module '/var/task/apps/api/src/routes/api-router' imported from /var/task/apps/api/src/app.js\n    at finalizeResolution (node:internal/modules/esm/resolve:280:11)\n    at moduleResolve (node:internal/modules/esm/resolve:865:10)\n    at moduleResolveWithNodePath (node:internal/modules/esm/resolve:989:14)\n    at defaultResolve (node:internal/modules/esm/resolve:1032:79)\n    at #cachedDefaultResolve (node:internal/modules/esm/loader:731:20)\n    at ModuleLoader.resolve (node:internal/modules/esm/loader:708:38)\n    at ModuleLoader.getModuleJobForImport (node:internal/modules/esm/loader:310:38)\n    at ModuleJob._link (node:internal/modules/esm/module_job:182:49)\n    at process.processTicksAndRejections (node:internal/process/task_queues:105:5) {\n  code: 'ERR_MODULE_NOT_FOUND',\n  url: 'file:///var/task/apps/api/src/routes/api-router'\n}\nNode.js process exited with exit status: 1. The logs above can help with debugging the issue.",
        "durationMs": "",
        "region": "",
        "maxMemoryUsed": "",
        "memorySize": "",
        "invocationId": "",
        "instanceId": "",
        "concurrency": ""
    },
    {
        "projectId": "prj_i3UGYgIq7KLxZ2Un1RP6LTT9EtI0",
        "TimeUTC": "2026-02-14 09:33:03",
        "timestampInMs": 1771061583305,
        "requestPath": "vendly-fubvhldmt-jeremiah-sentomeros-projects.vercel.app/",
        "requestMethod": "GET",
        "requestQueryString": "",
        "responseStatusCode": 500,
        "requestId": "x447b-1771061583305-ca0e5dd8f038",
        "requestUserAgent": "vercel-screenshot/1.0",
        "environment": "production",
        "branch": "main",
        "vercelCache": "MISS",
        "host": "vendly-fubvhldmt-jeremiah-sentomeros-projects.vercel.app",
        "deploymentDomain": "vendly-fubvhldmt-jeremiah-sentomeros-projects.vercel.app",
        "deploymentId": "dpl_EmTYLywybLy2yFBkrVU2L352dgdw",
        "traceId": "",
        "sessionId": "",
        "type": "function",
        "function": "/",
        "level": "",
        "message": "",
        "durationMs": 168,
        "region": "iad1",
        "maxMemoryUsed": -1,
        "memorySize": 2048,
        "invocationId": "01KHDQY7HRSVAKCE565BGPMTXC",
        "instanceId": "",
        "concurrency": -1
    },
    {
        "projectId": "prj_i3UGYgIq7KLxZ2Un1RP6LTT9EtI0",
        "TimeUTC": "2026-02-14 09:33:03",
        "timestampInMs": 1771061583986,
        "requestPath": "vendly-fubvhldmt-jeremiah-sentomeros-projects.vercel.app/",
        "requestMethod": "GET",
        "requestQueryString": "",
        "responseStatusCode": 500,
        "requestId": "tdvlk-1771061583259-a28899648d36",
        "requestUserAgent": "vercel-screenshot/1.0",
        "environment": "production",
        "branch": "main",
        "vercelCache": "MISS",
        "host": "vendly-fubvhldmt-jeremiah-sentomeros-projects.vercel.app",
        "deploymentDomain": "vendly-fubvhldmt-jeremiah-sentomeros-projects.vercel.app",
        "deploymentId": "dpl_EmTYLywybLy2yFBkrVU2L352dgdw",
        "traceId": "",
        "sessionId": "",
        "type": "function",
        "function": "/",
        "level": "error",
        "message": "Error [ERR_MODULE_NOT_FOUND]: Cannot find module '/var/task/apps/api/src/routes/api-router' imported from /var/task/apps/api/src/app.js\n    at finalizeResolution (node:internal/modules/esm/resolve:280:11)\n    at moduleResolve (node:internal/modules/esm/resolve:865:10)\n    at moduleResolveWithNodePath (node:internal/modules/esm/resolve:989:14)\n    at defaultResolve (node:internal/modules/esm/resolve:1032:79)\n    at #cachedDefaultResolve (node:internal/modules/esm/loader:731:20)\n    at ModuleLoader.resolve (node:internal/modules/esm/loader:708:38)\n    at ModuleLoader.getModuleJobForImport (node:internal/modules/esm/loader:310:38)\n    at ModuleJob._link (node:internal/modules/esm/module_job:182:49)\n    at process.processTicksAndRejections (node:internal/process/task_queues:105:5) {\n  code: 'ERR_MODULE_NOT_FOUND',\n  url: 'file:///var/task/apps/api/src/routes/api-router'\n}\nNode.js process exited with exit status: 1. The logs above can help with debugging the issue.\nError [ERR_MODULE_NOT_FOUND]: Cannot find module '/var/task/apps/api/src/routes/api-router' imported from /var/task/apps/api/src/app.js\n    at finalizeResolution (node:internal/modules/esm/resolve:280:11)\n    at moduleResolve (node:internal/modules/esm/resolve:865:10)\n    at moduleResolveWithNodePath (node:internal/modules/esm/resolve:989:14)\n    at defaultResolve (node:internal/modules/esm/resolve:1032:79)\n    at #cachedDefaultResolve (node:internal/modules/esm/loader:731:20)\n    at ModuleLoader.resolve (node:internal/modules/esm/loader:708:38)\n    at ModuleLoader.getModuleJobForImport (node:internal/modules/esm/loader:310:38)\n    at ModuleJob._link (node:internal/modules/esm/module_job:182:49)\n    at process.processTicksAndRejections (node:internal/process/task_queues:105:5) {\n  code: 'ERR_MODULE_NOT_FOUND',\n  url: 'file:///var/task/apps/api/src/routes/api-router'\n}\nNode.js process exited with exit status: 1. The logs above can help with debugging the issue.",
        "durationMs": "",
        "region": "",
        "maxMemoryUsed": "",
        "memorySize": "",
        "invocationId": "",
        "instanceId": "",
        "concurrency": ""
    },
    {
        "projectId": "prj_i3UGYgIq7KLxZ2Un1RP6LTT9EtI0",
        "TimeUTC": "2026-02-14 09:33:03",
        "timestampInMs": 1771061583259,
        "requestPath": "vendly-fubvhldmt-jeremiah-sentomeros-projects.vercel.app/",
        "requestMethod": "GET",
        "requestQueryString": "",
        "responseStatusCode": 500,
        "requestId": "tdvlk-1771061583259-a28899648d36",
        "requestUserAgent": "vercel-screenshot/1.0",
        "environment": "production",
        "branch": "main",
        "vercelCache": "MISS",
        "host": "vendly-fubvhldmt-jeremiah-sentomeros-projects.vercel.app",
        "deploymentDomain": "vendly-fubvhldmt-jeremiah-sentomeros-projects.vercel.app",
        "deploymentId": "dpl_EmTYLywybLy2yFBkrVU2L352dgdw",
        "traceId": "",
        "sessionId": "",
        "type": "function",
        "function": "/",
        "level": "",
        "message": "",
        "durationMs": 162,
        "region": "iad1",
        "maxMemoryUsed": -1,
        "memorySize": 2048,
        "invocationId": "01KHDQY7HPMZ7HGDVD3M5VAZZX",
        "instanceId": "",
        "concurrency": -1
    },
    {
        "projectId": "prj_i3UGYgIq7KLxZ2Un1RP6LTT9EtI0",
        "TimeUTC": "2026-02-14 09:33:03",
        "timestampInMs": 1771061583566,
        "requestPath": "vendly-fubvhldmt-jeremiah-sentomeros-projects.vercel.app/",
        "requestMethod": "GET",
        "requestQueryString": "",
        "responseStatusCode": "",
        "requestId": "24vgq-1771061583174-98efdb1e0ebc",
        "requestUserAgent": "Mozilla/5.0 (X11; Linux x86_64) AppleWebKit/537.36 (KHTML, like Gecko) HeadlessChrome/141.0.7390.0 Safari/537.36",
        "environment": "production",
        "branch": "main",
        "vercelCache": "",
        "host": "vendly-fubvhldmt-jeremiah-sentomeros-projects.vercel.app",
        "deploymentDomain": "vendly-fubvhldmt-jeremiah-sentomeros-projects.vercel.app",
        "deploymentId": "dpl_EmTYLywybLy2yFBkrVU2L352dgdw",
        "traceId": "",
        "sessionId": "",
        "type": "function",
        "function": "",
        "level": "error",
        "message": "Error [ERR_MODULE_NOT_FOUND]: Cannot find module '/var/task/apps/api/src/routes/api-router' imported from /var/task/apps/api/src/app.js\n    at finalizeResolution (node:internal/modules/esm/resolve:280:11)\n    at moduleResolve (node:internal/modules/esm/resolve:865:10)\n    at moduleResolveWithNodePath (node:internal/modules/esm/resolve:989:14)\n    at defaultResolve (node:internal/modules/esm/resolve:1032:79)\n    at #cachedDefaultResolve (node:internal/modules/esm/loader:731:20)\n    at ModuleLoader.resolve (node:internal/modules/esm/loader:708:38)\n    at ModuleLoader.getModuleJobForImport (node:internal/modules/esm/loader:310:38)\n    at ModuleJob._link (node:internal/modules/esm/module_job:182:49)\n    at process.processTicksAndRejections (node:internal/process/task_queues:105:5) {\n  code: 'ERR_MODULE_NOT_FOUND',\n  url: 'file:///var/task/apps/api/src/routes/api-router'\n}\nNode.js process exited with exit status: 1. The logs above can help with debugging the issue.",
        "durationMs": "",
        "region": "",
        "maxMemoryUsed": "",
        "memorySize": "",
        "invocationId": "",
        "instanceId": "",
        "concurrency": ""
    },
    {
        "projectId": "prj_i3UGYgIq7KLxZ2Un1RP6LTT9EtI0",
        "TimeUTC": "2026-02-14 09:33:03",
        "timestampInMs": 1771061583174,
        "requestPath": "vendly-fubvhldmt-jeremiah-sentomeros-projects.vercel.app/",
        "requestMethod": "GET",
        "requestQueryString": "",
        "responseStatusCode": "",
        "requestId": "24vgq-1771061583174-98efdb1e0ebc",
        "requestUserAgent": "Mozilla/5.0 (X11; Linux x86_64) AppleWebKit/537.36 (KHTML, like Gecko) HeadlessChrome/141.0.7390.0 Safari/537.36",
        "environment": "production",
        "branch": "main",
        "vercelCache": "",
        "host": "vendly-fubvhldmt-jeremiah-sentomeros-projects.vercel.app",
        "deploymentDomain": "vendly-fubvhldmt-jeremiah-sentomeros-projects.vercel.app",
        "deploymentId": "dpl_EmTYLywybLy2yFBkrVU2L352dgdw",
        "traceId": "",
        "sessionId": "",
        "type": "function",
        "function": "/",
        "level": "",
        "message": "",
        "durationMs": 135,
        "region": "iad1",
        "maxMemoryUsed": -1,
        "memorySize": 2048,
        "invocationId": "01KHDQY7HPMZ7HGDVD3PF8QEBK",
        "instanceId": "",
        "concurrency": -1
    },
    {
        "projectId": "prj_i3UGYgIq7KLxZ2Un1RP6LTT9EtI0",
        "TimeUTC": "2026-02-14 09:33:03",
        "timestampInMs": 1771061583712,
        "requestPath": "vendly-fubvhldmt-jeremiah-sentomeros-projects.vercel.app/",
        "requestMethod": "GET",
        "requestQueryString": "",
        "responseStatusCode": 500,
        "requestId": "vvv4f-1771061583125-e1f350bc7b1d",
        "requestUserAgent": "Mozilla/5.0 (X11; Linux x86_64) AppleWebKit/537.36 (KHTML, like Gecko) HeadlessChrome/141.0.7390.0 Safari/537.36",
        "environment": "production",
        "branch": "main",
        "vercelCache": "MISS",
        "host": "vendly-fubvhldmt-jeremiah-sentomeros-projects.vercel.app",
        "deploymentDomain": "vendly-fubvhldmt-jeremiah-sentomeros-projects.vercel.app",
        "deploymentId": "dpl_EmTYLywybLy2yFBkrVU2L352dgdw",
        "traceId": "",
        "sessionId": "",
        "type": "function",
        "function": "/",
        "level": "error",
        "message": "Error [ERR_MODULE_NOT_FOUND]: Cannot find module '/var/task/apps/api/src/routes/api-router' imported from /var/task/apps/api/src/app.js\n    at finalizeResolution (node:internal/modules/esm/resolve:280:11)\n    at moduleResolve (node:internal/modules/esm/resolve:865:10)\n    at moduleResolveWithNodePath (node:internal/modules/esm/resolve:989:14)\n    at defaultResolve (node:internal/modules/esm/resolve:1032:79)\n    at #cachedDefaultResolve (node:internal/modules/esm/loader:731:20)\n    at ModuleLoader.resolve (node:internal/modules/esm/loader:708:38)\n    at ModuleLoader.getModuleJobForImport (node:internal/modules/esm/loader:310:38)\n    at ModuleJob._link (node:internal/modules/esm/module_job:182:49)\n    at process.processTicksAndRejections (node:internal/process/task_queues:105:5) {\n  code: 'ERR_MODULE_NOT_FOUND',\n  url: 'file:///var/task/apps/api/src/routes/api-router'\n}\nNode.js process exited with exit status: 1. The logs above can help with debugging the issue.",
        "durationMs": "",
        "region": "",
        "maxMemoryUsed": "",
        "memorySize": "",
        "invocationId": "",
        "instanceId": "",
        "concurrency": ""
    },
    {
        "projectId": "prj_i3UGYgIq7KLxZ2Un1RP6LTT9EtI0",
        "TimeUTC": "2026-02-14 09:33:03",
        "timestampInMs": 1771061583125,
        "requestPath": "vendly-fubvhldmt-jeremiah-sentomeros-projects.vercel.app/",
        "requestMethod": "GET",
        "requestQueryString": "",
        "responseStatusCode": 500,
        "requestId": "vvv4f-1771061583125-e1f350bc7b1d",
        "requestUserAgent": "Mozilla/5.0 (X11; Linux x86_64) AppleWebKit/537.36 (KHTML, like Gecko) HeadlessChrome/141.0.7390.0 Safari/537.36",
        "environment": "production",
        "branch": "main",
        "vercelCache": "MISS",
        "host": "vendly-fubvhldmt-jeremiah-sentomeros-projects.vercel.app",
        "deploymentDomain": "vendly-fubvhldmt-jeremiah-sentomeros-projects.vercel.app",
        "deploymentId": "dpl_EmTYLywybLy2yFBkrVU2L352dgdw",
        "traceId": "",
        "sessionId": "",
        "type": "function",
        "function": "/",
        "level": "",
        "message": "",
        "durationMs": 136,
        "region": "iad1",
        "maxMemoryUsed": -1,
        "memorySize": 2048,
        "invocationId": "01KHDQY7KBH43A39JXYW87J0W6",
        "instanceId": "",
        "concurrency": -1
    }
]